asyntree/__init__.py
asyntree/__main__.py
asyntree/api.py
asyntree/cli.py
asyntree/parser.py
asyntree/py.typed
asyntree/visitor.py
asyntree-0.3.0.dist-info/WHEEL
asyntree-0.3.0.dist-info/entry_points.txt
asyntree-0.3.0.dist-info/METADATA
asyntree-0.3.0.dist-info/RECORD
