Metadata-Version: 2.3
Name: asyntree
Version: 0.3.0
Summary: Syntax trees and file utilities.
Author: Luke Miloszewski
Author-email: Luke Miloszewski <lukemiloszewski@gmail.com>
License: MIT
Classifier: Programming Language :: Python :: 3.12
Classifier: Programming Language :: Python :: 3.13
Requires-Dist: rich~=14.0
Requires-Dist: typer~=0.15
Requires-Python: >=3.12.0, <3.14.0
Project-URL: Changelog, https://github.com/lukemiloszewski/asyntree/releases
Project-URL: Homepage, https://github.com/lukemiloszewski/asyntree
Project-URL: Repository, https://github.com/lukemiloszewski/asyntree
